simplemind/__init__.py
simplemind/logging.py
simplemind/models.py
simplemind/settings.py
simplemind/utils.py
simplemind/providers/__init__.py
simplemind/providers/_base.py
simplemind/providers/_base_tools.py
simplemind/providers/amazon.py
simplemind/providers/anthropic.py
simplemind/providers/deepseek.py
simplemind/providers/gemini.py
simplemind/providers/groq.py
simplemind/providers/ollama.py
simplemind/providers/openai.py
simplemind/providers/xai.py
simplemind-0.3.2.dist-info/METADATA
simplemind-0.3.2.dist-info/WHEEL
simplemind-0.3.2.dist-info/licenses/LICENSE
simplemind-0.3.2.dist-info/RECORD
